setup.cfg
setup.py
src/twitter/__init__.py
src/twitter.common.app.egg-info/PKG-INFO
src/twitter.common.app.egg-info/SOURCES.txt
src/twitter.common.app.egg-info/dependency_links.txt
src/twitter.common.app.egg-info/namespace_packages.txt
src/twitter.common.app.egg-info/requires.txt
src/twitter.common.app.egg-info/top_level.txt
src/twitter.common.app.egg-info/zip-safe
src/twitter/common/__init__.py
src/twitter/common/app/__init__.py
src/twitter/common/app/application.py
src/twitter/common/app/inspection.py
src/twitter/common/app/module.py
src/twitter/common/app/modules/__init__.py