Metadata-Version: 1.0
Name: twitter.common.app
Version: 0.1.0
Summary: Twitter's Python application lifecycle framework.
Home-page: https://github.com/twitter/commons/tree/master/src/python/twitter/common/app
Author: UNKNOWN
Author-email: UNKNOWN
License: Apache License, Version 2.0
Platform: UNKNOWN
Classifier: Intended Audience :: Developers
Classifier: License :: OSI Approved :: Apache Software License
Classifier: Operating System :: OS Independent
Classifier: Programming Language :: Python
